canvelete/__init__.py
canvelete/auth.py
canvelete/client.py
canvelete/exceptions.py
canvelete/resources/__init__.py
canvelete/resources/api_keys.py
canvelete/resources/assets.py
canvelete/resources/billing.py
canvelete/resources/canvas.py
canvelete/resources/designs.py
canvelete/resources/render.py
canvelete/resources/templates.py
canvelete/resources/usage.py
canvelete/utils/__init__.py
canvelete/utils/retry.py
canvelete/utils/validation.py
canvelete/utils/webhooks.py
tests/__init__.py
tests/conftest.py
tests/test_assets.py
tests/test_canvas.py
tests/test_designs.py
tests/test_usage.py
canvelete-2.0.0.dist-info/METADATA
canvelete-2.0.0.dist-info/WHEEL
canvelete-2.0.0.dist-info/top_level.txt
canvelete-2.0.0.dist-info/RECORD
